pkg/__init__.py
pkg/lib1/__init__.py
pkg/lib1/eye_diagram.py
pkg/lib1/waveform.py
pkg/lib2/__init__.py
pkg/lib2/math_x.py
1_test_package-0.0.5.dist-info/License.txt
1_test_package-0.0.5.dist-info/METADATA
1_test_package-0.0.5.dist-info/WHEEL
1_test_package-0.0.5.dist-info/top_level.txt
1_test_package-0.0.5.dist-info/RECORD
