Metadata-Version: 2.1
Name: 1-test-package
Version: 0.0.5
Summary: My first upload test.
Home-page: UNKNOWN
Author: LBI5
Author-email: longfei.bai@3ds.com
License: UNKNOWN
Platform: UNKNOWN
Classifier: Programming Language :: Python :: 3
Classifier: License :: OSI Approved :: MIT License
Classifier: Operating System :: OS Independent
License-File: License.txt
